synctl/__init__.py
synctl/__version__.py
synctl/cli.py
synctl-2.1.5.dist-info/licenses/LICENSE
synctl-2.1.5.dist-info/METADATA
synctl-2.1.5.dist-info/WHEEL
synctl-2.1.5.dist-info/entry_points.txt
synctl-2.1.5.dist-info/top_level.txt
synctl-2.1.5.dist-info/RECORD
